clgpy/__init__.py
clgpy/_main_.py
clgpy-1.2.0.dist-info/LICENSE.txt
clgpy-1.2.0.dist-info/METADATA
clgpy-1.2.0.dist-info/WHEEL
clgpy-1.2.0.dist-info/top_level.txt
clgpy-1.2.0.dist-info/RECORD
