Metadata-Version: 2.1
Name: clgpy
Version: 1.2.0
Summary: clgpy is the package for any new programmer to work with Python.
Home-page: https://github.com/Rajatku301999mar/clgpypackage
Author: Rajat Kumar, Gurmehar Singh Soni
Author-email: rajatdj1999@gmail.com, gurmeharsoni.vit@gmail.com
License: MIT
Platform: UNKNOWN
Requires-Dist: numpy
